__init__.py
kisa.py
kisa-0.1.0a1.dist-info/LICENSE
kisa-0.1.0a1.dist-info/METADATA
kisa-0.1.0a1.dist-info/WHEEL
kisa-0.1.0a1.dist-info/top_level.txt
kisa-0.1.0a1.dist-info/RECORD
