Metadata-Version: 2.1
Name: kisa
Version: 0.1.0a1
Summary: Kisa is an advanced, comprehensive Object Oriented System written for Python.
Author-email: Noam Nisanov <noam.nisanov@gmail.com>
Maintainer-email: Noam Nisanov <noam.nisanov@gmail.com>
Project-URL: Homepage, https://github.com/nmnsnv/kisa
Keywords: OOP,Object Oriented,Object Oriented Programming
Classifier: Development Status :: 3 - Alpha
Classifier: Intended Audience :: Developers
Classifier: License :: OSI Approved :: MIT License
Classifier: Programming Language :: Python :: 3
Classifier: Programming Language :: Python :: 3.6
Classifier: Programming Language :: Python :: 3.7
Classifier: Programming Language :: Python :: 3.8
Classifier: Programming Language :: Python :: 3.9
Classifier: Programming Language :: Python :: 3.10
Classifier: Programming Language :: Python :: 3.11
Classifier: Programming Language :: Python :: 3 :: Only
Requires-Python: >=3.6
License-File: LICENSE
